AUTHORS.rst
CHANGES.rst
MANIFEST.in
README.rst
requirements-dev.txt
setup.py
docs/index.rst
multidimensional_urlencode/__init__.py
multidimensional_urlencode/urlencoder.py
multidimensional_urlencode.egg-info/PKG-INFO
multidimensional_urlencode.egg-info/SOURCES.txt
multidimensional_urlencode.egg-info/dependency_links.txt
multidimensional_urlencode.egg-info/not-zip-safe
multidimensional_urlencode.egg-info/top_level.txt