Metadata-Version: 1.1
Name: multidimensional_urlencode
Version: 0.0.4
Summary: Urlencode a multidimensional dict 
Home-page: https://github.com/uber/multidimensional_urlencode
Author: Sam Marcellus, Charles-Axel Dein
Author-email: charles@uber.com
License: MIT
Keywords: urlencode,params,multidimensional
Platform: any
Classifier: Programming Language :: Python
Classifier: Programming Language :: Python :: 2
Classifier: Programming Language :: Python :: 2.7
Classifier: Programming Language :: Python :: 3
Classifier: Programming Language :: Python :: 3.3
Classifier: Programming Language :: Python :: 3.4
Classifier: Programming Language :: Python :: 3.5
Classifier: Development Status :: 4 - Beta
Classifier: Environment :: Web Environment
Classifier: Intended Audience :: Developers
Classifier: License :: OSI Approved :: MIT License
Classifier: Operating System :: OS Independent
Classifier: Topic :: Software Development :: Libraries :: Python Modules
Classifier: Topic :: Internet :: WWW/HTTP
